liam/__about__.py
liam/__init__.py
liam/arn.py
liam/exception.py
liam/utils.py
liam/data/apigateway/2015-07-09/arns-1.json
liam/data/apigateway/2015-07-09/resources-1.json
liam/data/autoscaling/2011-01-01/arns-1.json
liam/data/autoscaling/2011-01-01/resources-1.json
liam/data/cloudformation/2010-05-15/arns-1.json
liam/data/cloudfront/2016-11-25/arns-1.json
liam/data/cloudwatch/2010-08-01/arns-1.json
liam/data/dynamodb/2012-08-10/arns-1.json
liam/data/ec2/2016-11-15/arns-1.json
liam/data/ec2/2016-11-15/paginators-1.json
liam/data/ec2/2016-11-15/resources-1.json
liam/data/ecs/2014-11-13/arns-1.json
liam/data/ecs/2014-11-13/resources-1.json
liam/data/efs/2015-02-01/arns-1.json
liam/data/efs/2015-02-01/paginators-1.json
liam/data/efs/2015-02-01/resources-1.json
liam/data/elasticache/2015-02-02/arns-1.json
liam/data/elasticache/2015-02-02/resources-1.json
liam/data/elasticbeanstalk/2010-12-01/arns-1.json
liam/data/elasticbeanstalk/2010-12-01/resources-1.json
liam/data/elb/2012-06-01/arns-1.json
liam/data/elb/2012-06-01/resources-1.json
liam/data/elbv2/2015-12-01/arns-1.json
liam/data/elbv2/2015-12-01/resources-1.json
liam/data/emr/2009-03-31/arns-1.json
liam/data/firehose/2015-08-04/arns-1.json
liam/data/firehose/2015-08-04/resources-1.json
liam/data/glacier/2012-06-01/arns-1.json
liam/data/iam/2010-05-08/arns-1.json
liam/data/kinesis/2013-12-02/arns-1.json
liam/data/kinesis/2013-12-02/resources-1.json
liam/data/kms/2014-11-01/arns-1.json
liam/data/kms/2014-11-01/resources-1.json
liam/data/lambda/2015-03-31/arns-1.json
liam/data/lambda/2015-03-31/resources-1.json
liam/data/logs/2014-03-28/arns-1.json
liam/data/logs/2014-03-28/resources-1.json
liam/data/opsworks/2013-02-18/arns-1.json
liam/data/rds/2014-10-31/arns-1.json
liam/data/rds/2014-10-31/resources-1.json
liam/data/redshift/2012-12-01/arns-1.json
liam/data/redshift/2012-12-01/resources-1.json
liam/data/route53/2013-04-01/arns-1.json
liam/data/route53/2013-04-01/resources-1.json
liam/data/s3/2006-03-01/arns-1.json
liam-0.1.0.dist-info/METADATA
liam-0.1.0.dist-info/WHEEL
liam-0.1.0.dist-info/top_level.txt
liam-0.1.0.dist-info/RECORD
