Metadata-Version: 2.1
Name: liam
Version: 0.1.0
Summary: I will look for you, I will find you, and I will delete you.
Home-page: https://github.com/racker/liam
Author: Rackers
Author-email: bruce.stringer@rackspace.com
License: UNKNOWN
Keywords: liam aws b682af8b
Platform: UNKNOWN
Classifier: Programming Language :: Python
Classifier: Programming Language :: Python :: 2
Classifier: Programming Language :: Python :: 2.7
Classifier: Programming Language :: Python :: 3
Classifier: Programming Language :: Python :: 3.5
Requires-Dist: boto3 (>=1.6.12)
Requires-Dist: botocore (>=1.9.12)
Provides-Extra: lint
Requires-Dist: flake8 (>=2.5.4) ; extra == 'lint'
Requires-Dist: pylint (>=1.5.5) ; extra == 'lint'
Provides-Extra: style
Requires-Dist: flake8 (>=2.5.4) ; extra == 'style'
Requires-Dist: pylint (>=1.5.5) ; extra == 'style'
Provides-Extra: test
Requires-Dist: coverage (>=4.0.3) ; extra == 'test'
Requires-Dist: moto (>=0.4.31) ; extra == 'test'
Requires-Dist: pytest (>=2.9.1) ; extra == 'test'
Requires-Dist: pytest-cov (>=2.4.0) ; extra == 'test'
Provides-Extra: test-requirements
Requires-Dist: coverage (>=4.0.3) ; extra == 'test-requirements'
Requires-Dist: moto (>=0.4.31) ; extra == 'test-requirements'
Requires-Dist: pytest (>=2.9.1) ; extra == 'test-requirements'
Requires-Dist: pytest-cov (>=2.4.0) ; extra == 'test-requirements'
Requires-Dist: flake8 (>=2.5.4) ; extra == 'test-requirements'
Requires-Dist: pylint (>=1.5.5) ; extra == 'test-requirements'
